ai_space/__init__.py
ai_space-0.0.1.dist-info/METADATA
ai_space-0.0.1.dist-info/WHEEL
ai_space-0.0.1.dist-info/RECORD
